[
  {
    "code": "DHA",
    "index": "VNINDEX",
    "lastPrice": 33.65,
    "changePrice1d": 2.2,
    "changePrice1dPct": 6.995230524642289,
    "accumulatedVal": 5444220000,
    "changeVol20p": 412.4920331421287,
    "avgVol20p": 39225.0,
    "changeVolPt1p": 0.0,
    "changeVolPt5p": 0.0,
    "avgVolTT20p": 39225.0,
    "lastUpdated": "2022-12-21 18:00",
    "totalPtVol5p": 0.0,
    "avgPtVal5p": 0.0
  },
  {
    "code": "SBT",
    "index": "VNINDEX",
    "lastPrice": 14.55,
    "changePrice1d": 0.95,
    "changePrice1dPct": 6.985294117647059,
    "accumulatedVal": 133742725000,
    "changeVol20p": 190.41269931328227,
    "avgVol20p": 4935070.0,
    "changeVolPt1p": 3.899507102302269,
    "changeVolPt5p": 37.99714382768685,
    "avgVolTT20p": 5769960.0,
    "lastUpdated": "2022-12-21 18:00",
    "totalPtVol5p": 10962100,
    "avgPtVal5p": 31682382000
  },
  {
    "code": "HAG",
    "index": "VNINDEX",
    "lastPrice": 8.91,
    "changePrice1d": 0.58,
    "changePrice1dPct": 6.9627851140456185,
    "accumulatedVal": 223519744000,
    "changeVol20p": 132.15924291849524,
    "avgVol20p": 20453280,
    "changeVolPt1p": 0.0,
    "changeVolPt5p": 0.6198203438387725,
    "avgVolTT20p": 20493035,
    "lastUpdated": "2022-12-21 18:00",
    "totalPtVol5p": 635100.0,
    "avgPtVal5p": 1136453600
  },
  {
    "code": "GIL",
    "index": "VNINDEX",
    "lastPrice": 22.65,
    "changePrice1d": 1.45,
    "changePrice1dPct": 6.839622641509434,
    "accumulatedVal": 106838065000,
    "changeVol20p": 283.70453283015075,
    "avgVol20p": 1791265.0,
    "changeVolPt1p": 0.0,
    "changeVolPt5p": 0.21592928704521985,
    "avgVolTT20p": 1852458.3,
    "lastUpdated": "2022-12-21 18:00",
    "totalPtVol5p": 20000.0,
    "avgPtVal5p": 84800000
  },
  {
    "code": "EVF",
    "index": "VNINDEX",
    "lastPrice": 7.3,
    "changePrice1d": 0.45,
    "changePrice1dPct": 6.569343065693431,
    "accumulatedVal": 5042887000,
    "changeVol20p": 250.8307649925102,
    "avgVol20p": 290395.0,
    "changeVolPt1p": 0.0,
    "changeVolPt5p": 178.74455947199496,
    "avgVolTT20p": 524995.0,
    "lastUpdated": "2022-12-21 18:00",
    "totalPtVol5p": 4692000.0,
    "avgPtVal5p": 6334200000
  },
  {
    "code": "STB",
    "index": "VNINDEX",
    "lastPrice": 23.55,
    "changePrice1d": 1.1,
    "changePrice1dPct": 4.8997772828507795,
    "accumulatedVal": 821735160000,
    "changeVol20p": 128.17637367534527,
    "avgVol20p": 27656735,
    "changeVolPt1p": 2.949085227486766,
    "changeVolPt5p": 1.3791099287663173,
    "avgVolTT20p": 27873050,
    "lastUpdated": "2022-12-21 18:00",
    "totalPtVol5p": 1922000.0,
    "avgPtVal5p": 8454980000
  },
  {
    "code": "LSS",
    "index": "VNINDEX",
    "lastPrice": 6.73,
    "changePrice1d": 0.29,
    "changePrice1dPct": 4.503105590062112,
    "accumulatedVal": 2421662000,
    "changeVol20p": 176.1211975471925,
    "avgVol20p": 207925.0,
    "changeVolPt1p": 0.0,
    "changeVolPt5p": 0.0,
    "avgVolTT20p": 207925.0,
    "lastUpdated": "2022-12-21 18:00",
    "totalPtVol5p": 0.0,
    "avgPtVal5p": 0.0
  },
  {
    "code": "HNG",
    "index": "VNINDEX",
    "lastPrice": 4.44,
    "changePrice1d": 0.16,
    "changePrice1dPct": 3.7383177570093458,
    "accumulatedVal": 23188155000,
    "changeVol20p": 73.65392440553917,
    "avgVol20p": 7286645.0,
    "changeVolPt1p": 0.0,
    "changeVolPt5p": 0.0,
    "avgVolTT20p": 7301645.0,
    "lastUpdated": "2022-12-21 18:00",
    "totalPtVol5p": 0.0,
    "avgPtVal5p": 0.0
  },
  {
    "code": "DPG",
    "index": "VNINDEX",
    "lastPrice": 27.5,
    "changePrice1d": 0.95,
    "changePrice1dPct": 3.5781544256120528,
    "accumulatedVal": 20060935000,
    "changeVol20p": 87.49511240061881,
    "avgVol20p": 882335.0,
    "changeVolPt1p": 0.0,
    "changeVolPt5p": 0.0,
    "avgVolTT20p": 899635.0,
    "lastUpdated": "2022-12-21 18:00",
    "totalPtVol5p": 0.0,
    "avgPtVal5p": 0.0
  },
  {
    "code": "ST8",
    "index": "VNINDEX",
    "lastPrice": 8.03,
    "changePrice1d": 0.27,
    "changePrice1dPct": 3.479381443298969,
    "accumulatedVal": 201040000,
    "changeVol20p": 109.28013876843018,
    "avgVol20p": 23060.0,
    "changeVolPt1p": 0.0,
    "changeVolPt5p": 0.0,
    "avgVolTT20p": 23060.0,
    "lastUpdated": "2022-12-21 18:00",
    "totalPtVol5p": 0.0,
    "avgPtVal5p": 0.0
  }
]